CHANGES.txt
LICENSE.txt
MANIFEST.in
README.txt
bootstrap.py
buildout.cfg
setup.py
src/m01/__init__.py
src/m01.zfs.egg-info/PKG-INFO
src/m01.zfs.egg-info/SOURCES.txt
src/m01.zfs.egg-info/dependency_links.txt
src/m01.zfs.egg-info/namespace_packages.txt
src/m01.zfs.egg-info/not-zip-safe
src/m01.zfs.egg-info/requires.txt
src/m01.zfs.egg-info/top_level.txt
src/m01/zfs/README.txt
src/m01/zfs/__init__.py
src/m01/zfs/base.py
src/m01/zfs/browser.py
src/m01/zfs/browser.zcml
src/m01/zfs/chunker.py
src/m01/zfs/configure.zcml
src/m01/zfs/exceptions.py
src/m01/zfs/interfaces.py
src/m01/zfs/item.py
src/m01/zfs/layer.py
src/m01/zfs/schema.py
src/m01/zfs/tests.py
src/m01/zfs/testing/__init__.py
src/m01/zfs/widget/__init__.py
src/m01/zfs/widget/configure.zcml
src/m01/zfs/widget/converter.py
src/m01/zfs/widget/error.py
src/m01/zfs/widget/widget_display.pt
src/m01/zfs/widget/widget_display.pt.py
src/m01/zfs/widget/widget_input.pt
src/m01/zfs/widget/widget_input.pt.py